LICENSE
README.rst
pyproject.toml
setup.cfg
setup.py
inkid/__init__.py
inkid.egg-info/PKG-INFO
inkid.egg-info/SOURCES.txt
inkid.egg-info/dependency_links.txt
inkid.egg-info/entry_points.txt
inkid.egg-info/not-zip-safe
inkid.egg-info/requires.txt
inkid.egg-info/top_level.txt
inkid/data/__init__.py
inkid/data/dataset.py
inkid/data/mathutils.c
inkid/data/mathutils.pxd
inkid/data/mathutils.pyx
inkid/data/ppm.py
inkid/data/test_Volume.py
inkid/data/volume.c
inkid/data/volume.pxd
inkid/data/volume.pyx
inkid/metrics/__init__.py
inkid/metrics/metrics.py
inkid/model/__init__.py
inkid/model/model.py
inkid/ops/__init__.py
inkid/ops/ops.py
inkid/ops/test_ops.py
inkid/schemas/__init__.py
inkid/schemas/dataSource0.1.schema.json
inkid/scripts/__init__.py
inkid/scripts/autoencoder.py
inkid/scripts/create_summary_images.py
inkid/scripts/descriptive_statistics.py
inkid/scripts/generate_subvolumes.py
inkid/scripts/metadata_to_xml.py
inkid/scripts/ppm_from_dummy_image.py
inkid/scripts/random_hyperparameters.py
inkid/scripts/rclone_upload.py
inkid/scripts/split_region_into_grid.py
inkid/scripts/surface_tif_to_ppm.py
inkid/scripts/test_scripts.py
inkid/scripts/train_and_predict.py
inkid/scripts/update_data_file.py
inkid/volumes/__init__.py
inkid/volumes/volume_protocol.py