Metadata-Version: 2.1
Name: inkid
Version: 0.0.7
Summary: Identify ink via machine learning
Home-page: https://gitlab.com/educelab/ink-id
Author: University of Kentucky
Author-email: stephen.parsons@uky.edu
License: GPLv3
Platform: UNKNOWN
Classifier: Programming Language :: Python :: 3
Classifier: Programming Language :: Python :: 3.8
Classifier: License :: OSI Approved :: GNU General Public License v3 (GPLv3)
Requires-Python: >=3.8
License-File: LICENSE
